{
  "no_wrap": true,
  "text_block_list": [
    {
      "text": "One day at the Tokyo Racecourse..."
    },
    {
      "name": "???",
      "text": "Hey, new trainer! Over here!"
    },
    {
      "name": "???",
      "text": "Tokyo Racecourse is as lively as ever! Do\nbe careful that you don't accidentally\nget separated."
    },
    {
      "name": "???",
      "text": "Now then, allow me to introduce myself."
    },
    {
      "choice_data_list": [
        "Thank you for bringing me on board."
      ],
      "color_text_info_list": [
        "★★★",
        "Hayakawa",
        "Tazuna"
      ],
      "name": "Tazuna Hayakawa",
      "text": "I'm Tazuna Hayakawa, secretary to the\ndirector, and I'll be your tour guide\ntoday!"
    },
    {
      "name": "Tazuna Hayakawa",
      "text": "Of course. ♪ I'm honored to be able to\nmeet a new trainer with as bright a\nfuture as yours!"
    },
    {
      "name": "Tazuna Hayakawa",
      "text": "In any case, we should get on with the\nacademy tour. But, before that..."
    },
    {
      "name": "Tazuna Hayakawa",
      "text": "A race is about to begin. Let's take a\nlook!"
    },
    {
      "name": "Tazuna Hayakawa",
      "text": "Can you hear the thunderous cheers\nfrom the crowd?"
    },
    {
      "text": "Wooooo!"
    },
    {
      "name": "Tazuna Hayakawa",
      "text": "People from all around the world adore\nUmamusume racing!"
    },
    {
      "name": "Tazuna Hayakawa",
      "text": "And with the fanfare, the curtains are\nraised on this stage where you and your\ntrainee will aim to achieve your dreams!"
    }
  ]
}